{"type": "FeatureCollection", "features": [{"type": "Feature", "geometry": {"type": "Point", "coordinates": [76.9558, 11.0168]}, "properties": {"id": "p_0", "name": "Isha Foundation (Sadhguru)", "short": "Environmental action, education and rural health initiatives.", "category": "", "city": "", "country": "", "level": 0, "website": ""}}]}